pdf_tools_mcp/__init__.py
pdf_tools_mcp/__main__.py
pdf_tools_mcp/server.py
pdf_tools_mcp-0.1.4.dist-info/METADATA
pdf_tools_mcp-0.1.4.dist-info/WHEEL
pdf_tools_mcp-0.1.4.dist-info/entry_points.txt
pdf_tools_mcp-0.1.4.dist-info/licenses/LICENSE
pdf_tools_mcp-0.1.4.dist-info/RECORD
