Metadata-Version: 2.4
Name: pdf-tools-mcp
Version: 0.1.4
Summary: A FastMCP-based PDF reading and manipulation tool server
Project-URL: Homepage, https://github.com/lockon-n/pdf-tools-mcp
Project-URL: Repository, https://github.com/lockon-n/pdf-tools-mcp
Project-URL: Documentation, https://github.com/lockon-n/pdf-tools-mcp#readme
Project-URL: Issues, https://github.com/lockon-n/pdf-tools-mcp/issues
Author-email: Junlong Li <lockonlvange@gmail.com>
Maintainer-email: Junlong Li <lockonlvange@gmail.com>
License: MIT
License-File: LICENSE
Keywords: fastmcp,mcp,pdf,pdf-manipulation,text-extraction
Classifier: Development Status :: 4 - Beta
Classifier: Intended Audience :: Developers
Classifier: License :: OSI Approved :: MIT License
Classifier: Operating System :: OS Independent
Classifier: Programming Language :: Python :: 3
Classifier: Programming Language :: Python :: 3.12
Classifier: Programming Language :: Python :: 3.13
Classifier: Topic :: Software Development :: Libraries :: Python Modules
Classifier: Topic :: Text Processing :: Markup
Classifier: Topic :: Utilities
Requires-Python: >=3.12
Requires-Dist: fastmcp>=2.10.5
Requires-Dist: httpx>=0.28.1
Requires-Dist: mcp[cli]>=1.11.0
Requires-Dist: pypdf2>=3.0.1
Requires-Dist: requests>=2.25.0
